leap_labs_test/UIE.py
leap_labs_test/__init__.py
leap_labs_test/config_handler.py
leap_labs_test/event_handler.py
leap_labs_test/generation.py
leap_labs_test/generation_tf.py
leap_labs_test/logging_handler.py
leap_labs_test/objectives.py
leap_labs_test/objectives_tf.py
leap_labs_test/saliency.py
leap_labs_test/saliency_tf.py
leap_labs_test/transforms.py
leap_labs_test/transforms_tf.py
leap_labs_test/utils.py
leap_labs_test/vega_charts.py
leap_temp/UIE.cpython-39-darwin.so
leap_temp/UIE.py
leap_temp/__init__.cpython-39-darwin.so
leap_temp/__init__.py
leap_temp/config_handler.cpython-39-darwin.so
leap_temp/config_handler.py
leap_temp/event_handler.cpython-39-darwin.so
leap_temp/event_handler.py
leap_temp/generation.cpython-39-darwin.so
leap_temp/generation.py
leap_temp/generation_tf.cpython-39-darwin.so
leap_temp/generation_tf.py
leap_temp/logging_handler.cpython-39-darwin.so
leap_temp/logging_handler.py
leap_temp/objectives.cpython-39-darwin.so
leap_temp/objectives.py
leap_temp/objectives_tf.cpython-39-darwin.so
leap_temp/objectives_tf.py
leap_temp/saliency.cpython-39-darwin.so
leap_temp/saliency.py
leap_temp/saliency_tf.cpython-39-darwin.so
leap_temp/saliency_tf.py
leap_temp/setup.cpython-39-darwin.so
leap_temp/setup.py
leap_temp/transforms.cpython-39-darwin.so
leap_temp/transforms.py
leap_temp/transforms_tf.cpython-39-darwin.so
leap_temp/transforms_tf.py
leap_temp/utils.cpython-39-darwin.so
leap_temp/utils.py
leap_temp/vega_charts.cpython-39-darwin.so
leap_temp/vega_charts.py
leap_labs_test-0.1.1.dist-info/METADATA
leap_labs_test-0.1.1.dist-info/WHEEL
leap_labs_test-0.1.1.dist-info/top_level.txt
leap_labs_test-0.1.1.dist-info/RECORD
